hcr/__main__.py
hcr/main/__init__.py
hcr/main/constants.py
hcr/main/dataset.py
hcr/main/dense.py
hcr/main/diagram.py
hcr/main/diagram_optimizer.py
hcr/main/draw_pad.py
hcr/main/register_buttons.py
hcr/main/runtime.py
hcr-1.2.0.dev1.dist-info/LICENSE
hcr-1.2.0.dev1.dist-info/METADATA
hcr-1.2.0.dev1.dist-info/WHEEL
hcr-1.2.0.dev1.dist-info/entry_points.txt
hcr-1.2.0.dev1.dist-info/top_level.txt
hcr-1.2.0.dev1.dist-info/RECORD
