Metadata-Version: 2.1
Name: hcr
Version: 1.2.0.dev1
Summary: Visualizing the beauty of neural networks
Home-page: https://github.com/nvfp/Handwritten-Character-Recognition
Author: Nicholas Valentinus
Author-email: nvfastplease@gmail.com
License: MIT
Project-URL: documentation, https://github.com/nvfp/Handwritten-Character-Recognition
Project-URL: report bugs, https://github.com/nvfp/Handwritten-Character-Recognition/issues
Project-URL: repo, https://github.com/nvfp/Handwritten-Character-Recognition
Project-URL: changelog, https://nvfp.github.io/mykit/Handwritten-Character-Recognition#changelog
Keywords: python,machine learning,neural networks
Classifier: Topic :: Scientific/Engineering
Classifier: License :: OSI Approved :: MIT License
Classifier: Operating System :: OS Independent
Classifier: Programming Language :: Python
Classifier: Programming Language :: Python :: 3
Classifier: Programming Language :: Python :: 3.8
Classifier: Programming Language :: Python :: 3.9
Classifier: Programming Language :: Python :: 3.10
Classifier: Natural Language :: English
Requires-Python: >=3.8
License-File: LICENSE
Requires-Dist: mykit (==2.0.2)
Requires-Dist: numba (==0.55.2)
Requires-Dist: numpy (==1.22.4)
